enhanced_logger/__init__.py
enhanced_logger/enhanced_logger.py
enhanced_logger-0.1.3.dist-info/LICENSE
enhanced_logger-0.1.3.dist-info/METADATA
enhanced_logger-0.1.3.dist-info/WHEEL
enhanced_logger-0.1.3.dist-info/top_level.txt
enhanced_logger-0.1.3.dist-info/RECORD
