Metadata-Version: 2.1
Name: enhanced-logger
Version: 0.1.3
Summary: An enhanced logging package for Python with additional features and performance metrics.
Home-page: https://github.com/Rohan7654/enhanced_logger_package.git
Author: ROHAN
Author-email: rohanroni2019@gmail.com
License: MIT
Classifier: Intended Audience :: Developers
Classifier: License :: OSI Approved :: MIT License
Classifier: Programming Language :: Python :: 3
Classifier: Programming Language :: Python :: 3.6
Classifier: Programming Language :: Python :: 3.7
Classifier: Programming Language :: Python :: 3.8
Classifier: Programming Language :: Python :: 3.9
Classifier: Programming Language :: Python :: 3.10
Classifier: Programming Language :: Python :: 3.11
Classifier: Programming Language :: Python :: 3.12
Classifier: Topic :: Software Development :: Libraries :: Python Modules
Requires-Python: >=3.6
License-File: LICENSE
Requires-Dist: requests
Requires-Dist: psutil
Requires-Dist: pymongo
Requires-Dist: psycopg2-binary
